MANIFEST.in
README.rst
setup.py
admin_jqueryui/__init__.py
admin_jqueryui/static/admin_jqueryui/js/admin_jqueryui.min.js
django_admin_jqueryui112.egg-info/PKG-INFO
django_admin_jqueryui112.egg-info/SOURCES.txt
django_admin_jqueryui112.egg-info/dependency_links.txt
django_admin_jqueryui112.egg-info/top_level.txt